Metadata-Version: 2.1
Name: swapnilcalculator
Version: 0.0.1
Summary: Very very basic calculator for trial
Home-page: UNKNOWN
Author: swapnil
Author-email: swapniljt85@gmail.com
License: MIT
Keywords: calculator
Platform: UNKNOWN
Classifier: Programming Language :: Python :: 3
Classifier: License :: OSI Approved :: MIT License
Classifier: Operating System :: OS Independent
License-File: LICENSE.txt
